[
  {
    "id": 0,
    "name": "FLUMBO",
    "numberOfEmployees": 6,
    "dateFrom": "2016-02-29",
    "employees": [
      {
        "id": 0,
        "name": "Graham Rocha"
      },
      {
        "id": 1,
        "name": "Peterson Rich"
      },
      {
        "id": 2,
        "name": "Sara Melton"
      }
    ]
  },
  {
    "id": 1,
    "name": "NUTRALAB",
    "numberOfEmployees": 6,
    "dateFrom": "2015-09-29",
    "employees": [
      {
        "id": 0,
        "name": "Maricela Woodward"
      },
      {
        "id": 1,
        "name": "Duke Palmer"
      },
      {
        "id": 2,
        "name": "Romero Oneil"
      },
      {
        "id": 3,
        "name": "Jasmine Finch"
      },
      {
        "id": 4,
        "name": "Josefina Reese"
      }
    ]
  },
  {
    "id": 2,
    "name": "ENTROFLEX",
    "numberOfEmployees": 5,
    "dateFrom": "2014-02-01",
    "employees": [
      {
        "id": 0,
        "name": "Katheryn Gould"
      },
      {
        "id": 1,
        "name": "Ann Mullins"
      },
      {
        "id": 2,
        "name": "Chang Douglas"
      },
      {
        "id": 3,
        "name": "Gordon Sawyer"
      },
      {
        "id": 4,
        "name": "Fleming Murphy"
      }
    ]
  },
  {
    "id": 3,
    "name": "ZOARERE",
    "numberOfEmployees": 6,
    "dateFrom": "2016-05-03",
    "employees": [
      {
        "id": 0,
        "name": "Carey Morton"
      },
      {
        "id": 1,
        "name": "Lupe Hill"
      },
      {
        "id": 2,
        "name": "Robert Stuart"
      },
      {
        "id": 3,
        "name": "Snow Sexton"
      }
    ]
  },
  {
    "id": 4,
    "name": "OVERFORK",
    "numberOfEmployees": 2,
    "dateFrom": "2017-01-15",
    "employees": [
      {
        "id": 0,
        "name": "Cara Terry"
      },
      {
        "id": 1,
        "name": "Tran Anderson"
      },
      {
        "id": 2,
        "name": "Roberson Callahan"
      },
      {
        "id": 3,
        "name": "Sweet Suarez"
      },
      {
        "id": 4,
        "name": "Leta Morales"
      }
    ]
  },
  {
    "id": 5,
    "name": "MITROC",
    "numberOfEmployees": 6,
    "dateFrom": "2016-01-30",
    "employees": [
      {
        "id": 0,
        "name": "Ingram Osborn"
      },
      {
        "id": 1,
        "name": "Diana Floyd"
      }
    ]
  },
  {
    "id": 6,
    "name": "ENTHAZE",
    "numberOfEmployees": 1,
    "dateFrom": "2015-04-21",
    "employees": [
      {
        "id": 0,
        "name": "Neva Spears"
      },
      {
        "id": 1,
        "name": "Debora Burgess"
      },
      {
        "id": 2,
        "name": "Robles Obrien"
      },
      {
        "id": 3,
        "name": "Adele Jackson"
      },
      {
        "id": 4,
        "name": "Mccormick Snider"
      },
      {
        "id": 5,
        "name": "Giles Reed"
      }
    ]
  }
]